getpricedata/__init__.py
getpricedata/getETFprice.py
pytech/__init__.py
pytech/pytech.cp39-win_amd64.pyd
pytech_zp-0.1.5.dist-info/LICENSE
pytech_zp-0.1.5.dist-info/METADATA
pytech_zp-0.1.5.dist-info/WHEEL
pytech_zp-0.1.5.dist-info/top_level.txt
pytech_zp-0.1.5.dist-info/RECORD
