Metadata-Version: 2.1
Name: pytech-zp
Version: 0.1.5
Summary: Python function package of technical indicators and patterns implemented by C++
Author: Peng Zhao
Author-email: zhaokehan86@163.com
License: Copyright (c) 2018 The Python Packaging Authority
License-File: LICENSE
Requires-Dist: numpy
Requires-Dist: pandas
Requires-Dist: pyodbc
